eosvc/__init__.py
eosvc/cli.py
eosvc/helpers.py
eosvc-0.1.2.dist-info/licenses/LICENSE
eosvc-0.1.2.dist-info/METADATA
eosvc-0.1.2.dist-info/WHEEL
eosvc-0.1.2.dist-info/entry_points.txt
eosvc-0.1.2.dist-info/top_level.txt
eosvc-0.1.2.dist-info/RECORD
