Metadata-Version: 2.4
Name: eosvc
Version: 0.1.2
Summary: EOSVC (Ersilia Version Control) is a Python-based tool designed to unify code versioning with data and result management by combining Git and S3 workflows around the main branch. 
Author-email: Abel Legese <abel@ersilia.io>, Miquel Duran-Frigola <miquel@ersilia.io>
License:                     GNU GENERAL PUBLIC LICENSE
Requires-Python: >=3.10
License-File: LICENSE
Requires-Dist: loguru
Requires-Dist: rich
Requires-Dist: boto3
Requires-Dist: ruff>=0.14.10
Requires-Dist: python-dotenv
Provides-Extra: dev
Requires-Dist: pytest; extra == "dev"
Requires-Dist: black; extra == "dev"
Requires-Dist: flake8; extra == "dev"
Dynamic: license-file
